open_weather_easy/__init__.py
open_weather_easy/main.py
open_weather_easy-0.1.dist-info/METADATA
open_weather_easy-0.1.dist-info/WHEEL
open_weather_easy-0.1.dist-info/top_level.txt
open_weather_easy-0.1.dist-info/RECORD
