Metadata-Version: 2.1
Name: open-weather-easy
Version: 0.1
Summary: A simple library to use OpenWeatherMap API
Home-page: https://github.com/yourusername/open_weather_easy
Author: Radin Abdorazaghi
Author-email: your_email@example.com
License: UNKNOWN
Platform: UNKNOWN
Classifier: Programming Language :: Python :: 3
Classifier: License :: OSI Approved :: MIT License
Classifier: Operating System :: OS Independent
Requires-Python: >=3.6
Requires-Dist: requests
